LICENSE
README.md
setup.cfg
setup.py
django_ip_restrictor.egg-info/PKG-INFO
django_ip_restrictor.egg-info/SOURCES.txt
django_ip_restrictor.egg-info/dependency_links.txt
django_ip_restrictor.egg-info/requires.txt
django_ip_restrictor.egg-info/top_level.txt
ip_restrictor/__init__.py
ip_restrictor/decorators.py
ip_restrictor/middleware.py
ip_restrictor/mixins.py
ip_restrictor/settings.py
ip_restrictor/utils.py