Metadata-Version: 2.1
Name: django-ip-restrictor
Version: 0.1.0
Summary: A Django package to restrict views based on IP addresses.
Home-page: https://github.com/sudoAlireza/django-ip-restrictor
Author: Alireza Fathi
Author-email: alirezafathi.ce@gmail.com
License: MIT
Classifier: Framework :: Django
Classifier: Programming Language :: Python :: 3
Classifier: License :: OSI Approved :: MIT License
Requires-Python: >=3.7
License-File: LICENSE
Requires-Dist: Django>=3.2
